{
    "fluentMethods": true,
    "relationships": [
        {
            "relationshipType": "one-to-many",
            "relationshipName": "secoes",
            "otherEntityName": "secao",
            "otherEntityRelationshipName": "statusContagem"
        },
        {
            "relationshipType": "one-to-many",
            "relationshipName": "contagens",
            "otherEntityName": "contagem",
            "otherEntityRelationshipName": "statusContagem"
        }
    ],
    "fields": [
        {
            "fieldName": "descricao",
            "fieldType": "String"
        }
    ],
    "changelogDate": "20180430164133",
    "entityTableName": "status_contagem",
    "dto": "no",
    "pagination": "no",
    "service": "no",
    "jpaMetamodelFiltering": false
}